[
  {
    "dt": 1778382000,
    "weather": [
      {
        "id": 801,
        "main": "Clouds",
        "description": "few clouds",
        "icon": "02d"
      }
    ],
    "main": {
      "temp": 297.65,
      "feels_like": 296.76,
      "temp_min": 297.65,
      "temp_max": 297.65,
      "pressure": 1009,
      "sea_level": 1009,
      "grnd_level": 1000,
      "humidity": 23,
      "temp_kf": 0
    },
    "wind": {
      "speed": 7.64,
      "deg": 271,
      "gust": 9.3
    },
    "clouds": {
      "all": 20
    }
  },
  {
    "dt": 1778392800,
    "weather": [
      {
        "id": 801,
        "main": "Clouds",
        "description": "few clouds",
        "icon": "02d"
      }
    ],
    "main": {
      "temp": 297.58,
      "feels_like": 296.71,
      "temp_min": 297.44,
      "temp_max": 297.58,
      "pressure": 1008,
      "sea_level": 1008,
      "grnd_level": 998,
      "humidity": 24,
      "temp_kf": 0.14
    },
    "wind": {
      "speed": 7.8,
      "deg": 274,
      "gust": 7.96
    },
    "clouds": {
      "all": 24
    }
  },
  {
    "dt": 1778403600,
    "weather": [
      {
        "id": 802,
        "main": "Clouds",
        "description": "scattered clouds",
        "icon": "03d"
      }
    ],
    "main": {
      "temp": 296.1,
      "feels_like": 295.13,
      "temp_min": 295.32,
      "temp_max": 296.1,
      "pressure": 1008,
      "sea_level": 1008,
      "grnd_level": 998,
      "humidity": 26,
      "temp_kf": 0.78
    },
    "wind": {
      "speed": 7.17,
      "deg": 206,
      "gust": 11.33
    },
    "clouds": {
      "all": 25
    }
  },
  {
    "dt": 1778414400,
    "weather": [
      {
        "id": 802,
        "main": "Clouds",
        "description": "scattered clouds",
        "icon": "03n"
      }
    ],
    "main": {
      "temp": 287.91,
      "feels_like": 286.77,
      "temp_min": 287.91,
      "temp_max": 287.91,
      "pressure": 1008,
      "sea_level": 1008,
      "grnd_level": 999,
      "humidity": 51,
      "temp_kf": 0
    },
    "wind": {
      "speed": 5.02,
      "deg": 207,
      "gust": 10.25
    },
    "clouds": {
      "all": 34
    }
  },
  {
    "dt": 1778425200,
    "weather": [
      {
        "id": 800,
        "main": "Clear",
        "description": "clear sky",
        "icon": "01n"
      }
    ],
    "main": {
      "temp": 286.45,
      "feels_like": 285.51,
      "temp_min": 286.45,
      "temp_max": 286.45,
      "pressure": 1008,
      "sea_level": 1008,
      "grnd_level": 999,
      "humidity": 64,
      "temp_kf": 0
    },
    "wind": {
      "speed": 5.08,
      "deg": 200,
      "gust": 9.79
    },
    "clouds": {
      "all": 9
    }
  },
  {
    "dt": 1778436000,
    "weather": [
      {
        "id": 800,
        "main": "Clear",
        "description": "clear sky",
        "icon": "01n"
      }
    ],
    "main": {
      "temp": 284.27,
      "feels_like": 283.34,
      "temp_min": 284.27,
      "temp_max": 284.27,
      "pressure": 1008,
      "sea_level": 1008,
      "grnd_level": 999,
      "humidity": 73,
      "temp_kf": 0
    },
    "wind": {
      "speed": 4.49,
      "deg": 195,
      "gust": 9.58
    },
    "clouds": {
      "all": 6
    }
  },
  {
    "dt": 1778446800,
    "weather": [
      {
        "id": 800,
        "main": "Clear",
        "description": "clear sky",
        "icon": "01d"
      }
    ],
    "main": {
      "temp": 284.54,
      "feels_like": 283.67,
      "temp_min": 284.54,
      "temp_max": 284.54,
      "pressure": 1009,
      "sea_level": 1009,
      "grnd_level": 999,
      "humidity": 74,
      "temp_kf": 0
    },
    "wind": {
      "speed": 4.19,
      "deg": 211,
      "gust": 8.92
    },
    "clouds": {
      "all": 4
    }
  },
  {
    "dt": 1778457600,
    "weather": [
      {
        "id": 801,
        "main": "Clouds",
        "description": "few clouds",
        "icon": "02d"
      }
    ],
    "main": {
      "temp": 291.91,
      "feels_like": 291.17,
      "temp_min": 291.91,
      "temp_max": 291.91,
      "pressure": 1008,
      "sea_level": 1008,
      "grnd_level": 999,
      "humidity": 51,
      "temp_kf": 0
    },
    "wind": {
      "speed": 4.93,
      "deg": 236,
      "gust": 6
    },
    "clouds": {
      "all": 13
    }
  },
  {
    "dt": 1778468400,
    "weather": [
      {
        "id": 804,
        "main": "Clouds",
        "description": "overcast clouds",
        "icon": "04d"
      }
    ],
    "main": {
      "temp": 296.66,
      "feels_like": 296.03,
      "temp_min": 296.66,
      "temp_max": 296.66,
      "pressure": 1007,
      "sea_level": 1007,
      "grnd_level": 997,
      "humidity": 37,
      "temp_kf": 0
    },
    "wind": {
      "speed": 5.53,
      "deg": 256,
      "gust": 6.81
    },
    "clouds": {
      "all": 87
    }
  },
  {
    "dt": 1778479200,
    "weather": [
      {
        "id": 804,
        "main": "Clouds",
        "description": "overcast clouds",
        "icon": "04d"
      }
    ],
    "main": {
      "temp": 297.48,
      "feels_like": 296.88,
      "temp_min": 297.48,
      "temp_max": 297.48,
      "pressure": 1006,
      "sea_level": 1006,
      "grnd_level": 996,
      "humidity": 35,
      "temp_kf": 0
    },
    "wind": {
      "speed": 6.06,
      "deg": 242,
      "gust": 9.12
    },
    "clouds": {
      "all": 94
    }
  },
  {
    "dt": 1778490000,
    "weather": [
      {
        "id": 500,
        "main": "Rain",
        "description": "light rain",
        "icon": "10d"
      }
    ],
    "main": {
      "temp": 290.14,
      "feels_like": 289.88,
      "temp_min": 290.14,
      "temp_max": 290.14,
      "pressure": 1007,
      "sea_level": 1007,
      "grnd_level": 997,
      "humidity": 76,
      "temp_kf": 0
    },
    "wind": {
      "speed": 7.44,
      "deg": 298,
      "gust": 10.53
    },
    "rain": {
      "3h": 1.71
    },
    "clouds": {
      "all": 100
    }
  },
  {
    "dt": 1778500800,
    "weather": [
      {
        "id": 500,
        "main": "Rain",
        "description": "light rain",
        "icon": "10n"
      }
    ],
    "main": {
      "temp": 289.03,
      "feels_like": 288.61,
      "temp_min": 289.03,
      "temp_max": 289.03,
      "pressure": 1008,
      "sea_level": 1008,
      "grnd_level": 999,
      "humidity": 74,
      "temp_kf": 0
    },
    "wind": {
      "speed": 2.88,
      "deg": 228,
      "gust": 6.31
    },
    "rain": {
      "3h": 0.47
    },
    "clouds": {
      "all": 100
    }
  },
  {
    "dt": 1778511600,
    "weather": [
      {
        "id": 804,
        "main": "Clouds",
        "description": "overcast clouds",
        "icon": "04n"
      }
    ],
    "main": {
      "temp": 287.3,
      "feels_like": 286.86,
      "temp_min": 287.3,
      "temp_max": 287.3,
      "pressure": 1008,
      "sea_level": 1008,
      "grnd_level": 998,
      "humidity": 80,
      "temp_kf": 0
    },
    "wind": {
      "speed": 4.14,
      "deg": 231,
      "gust": 10.58
    },
    "clouds": {
      "all": 85
    }
  },
  {
    "dt": 1778522400,
    "weather": [
      {
        "id": 500,
        "main": "Rain",
        "description": "light rain",
        "icon": "10n"
      }
    ],
    "main": {
      "temp": 285.54,
      "feels_like": 284.61,
      "temp_min": 285.54,
      "temp_max": 285.54,
      "pressure": 1007,
      "sea_level": 1007,
      "grnd_level": 998,
      "humidity": 68,
      "temp_kf": 0
    },
    "wind": {
      "speed": 3.58,
      "deg": 188,
      "gust": 7.36
    },
    "rain": {
      "3h": 0.1
    },
    "clouds": {
      "all": 92
    }
  },
  {
    "dt": 1778533200,
    "weather": [
      {
        "id": 500,
        "main": "Rain",
        "description": "light rain",
        "icon": "10d"
      }
    ],
    "main": {
      "temp": 284.68,
      "feels_like": 283.82,
      "temp_min": 284.68,
      "temp_max": 284.68,
      "pressure": 1007,
      "sea_level": 1007,
      "grnd_level": 998,
      "humidity": 74,
      "temp_kf": 0
    },
    "wind": {
      "speed": 3.58,
      "deg": 202,
      "gust": 8.13
    },
    "rain": {
      "3h": 0.31
    },
    "clouds": {
      "all": 100
    }
  },
  {
    "dt": 1778544000,
    "weather": [
      {
        "id": 804,
        "main": "Clouds",
        "description": "overcast clouds",
        "icon": "04d"
      }
    ],
    "main": {
      "temp": 292.66,
      "feels_like": 292,
      "temp_min": 292.66,
      "temp_max": 292.66,
      "pressure": 1007,
      "sea_level": 1007,
      "grnd_level": 998,
      "humidity": 51,
      "temp_kf": 0
    },
    "wind": {
      "speed": 5.97,
      "deg": 213,
      "gust": 8.04
    },
    "clouds": {
      "all": 100
    }
  },
  {
    "dt": 1778554800,
    "weather": [
      {
        "id": 803,
        "main": "Clouds",
        "description": "broken clouds",
        "icon": "04d"
      }
    ],
    "main": {
      "temp": 298.12,
      "feels_like": 297.69,
      "temp_min": 298.12,
      "temp_max": 298.12,
      "pressure": 1005,
      "sea_level": 1005,
      "grnd_level": 996,
      "humidity": 39,
      "temp_kf": 0
    },
    "wind": {
      "speed": 5.77,
      "deg": 209,
      "gust": 7.33
    },
    "clouds": {
      "all": 83
    }
  },
  {
    "dt": 1778565600,
    "weather": [
      {
        "id": 803,
        "main": "Clouds",
        "description": "broken clouds",
        "icon": "04d"
      }
    ],
    "main": {
      "temp": 299.8,
      "feels_like": 299.8,
      "temp_min": 299.8,
      "temp_max": 299.8,
      "pressure": 1003,
      "sea_level": 1003,
      "grnd_level": 994,
      "humidity": 33,
      "temp_kf": 0
    },
    "wind": {
      "speed": 7.07,
      "deg": 212,
      "gust": 8.65
    },
    "clouds": {
      "all": 84
    }
  },
  {
    "dt": 1778576400,
    "weather": [
      {
        "id": 801,
        "main": "Clouds",
        "description": "few clouds",
        "icon": "02d"
      }
    ],
    "main": {
      "temp": 296.46,
      "feels_like": 295.89,
      "temp_min": 296.46,
      "temp_max": 296.46,
      "pressure": 1002,
      "sea_level": 1002,
      "grnd_level": 993,
      "humidity": 40,
      "temp_kf": 0
    },
    "wind": {
      "speed": 7.17,
      "deg": 203,
      "gust": 11.88
    },
    "clouds": {
      "all": 16
    }
  },
  {
    "dt": 1778587200,
    "weather": [
      {
        "id": 500,
        "main": "Rain",
        "description": "light rain",
        "icon": "10n"
      }
    ],
    "main": {
      "temp": 291.45,
      "feels_like": 290.62,
      "temp_min": 291.45,
      "temp_max": 291.45,
      "pressure": 1004,
      "sea_level": 1004,
      "grnd_level": 994,
      "humidity": 49,
      "temp_kf": 0
    },
    "wind": {
      "speed": 8.03,
      "deg": 215,
      "gust": 16.36
    },
    "rain": {
      "3h": 0.17
    },
    "clouds": {
      "all": 58
    }
  },
  {
    "dt": 1778598000,
    "weather": [
      {
        "id": 804,
        "main": "Clouds",
        "description": "overcast clouds",
        "icon": "04n"
      }
    ],
    "main": {
      "temp": 288.3,
      "feels_like": 287.41,
      "temp_min": 288.3,
      "temp_max": 288.3,
      "pressure": 1005,
      "sea_level": 1005,
      "grnd_level": 996,
      "humidity": 59,
      "temp_kf": 0
    },
    "wind": {
      "speed": 3.7,
      "deg": 182,
      "gust": 6.84
    },
    "clouds": {
      "all": 100
    }
  },
  {
    "dt": 1778608800,
    "weather": [
      {
        "id": 500,
        "main": "Rain",
        "description": "light rain",
        "icon": "10n"
      }
    ],
    "main": {
      "temp": 285.85,
      "feels_like": 285.03,
      "temp_min": 285.85,
      "temp_max": 285.85,
      "pressure": 1007,
      "sea_level": 1007,
      "grnd_level": 997,
      "humidity": 71,
      "temp_kf": 0
    },
    "wind": {
      "speed": 3.16,
      "deg": 143,
      "gust": 5.66
    },
    "rain": {
      "3h": 0.24
    },
    "clouds": {
      "all": 95
    }
  },
  {
    "dt": 1778619600,
    "weather": [
      {
        "id": 500,
        "main": "Rain",
        "description": "light rain",
        "icon": "10d"
      }
    ],
    "main": {
      "temp": 286.77,
      "feels_like": 286.17,
      "temp_min": 286.77,
      "temp_max": 286.77,
      "pressure": 1009,
      "sea_level": 1009,
      "grnd_level": 999,
      "humidity": 76,
      "temp_kf": 0
    },
    "wind": {
      "speed": 2.61,
      "deg": 127,
      "gust": 5.35
    },
    "rain": {
      "3h": 0.11
    },
    "clouds": {
      "all": 100
    }
  },
  {
    "dt": 1778630400,
    "weather": [
      {
        "id": 500,
        "main": "Rain",
        "description": "light rain",
        "icon": "10d"
      }
    ],
    "main": {
      "temp": 291.33,
      "feels_like": 290.72,
      "temp_min": 291.33,
      "temp_max": 291.33,
      "pressure": 1010,
      "sea_level": 1010,
      "grnd_level": 1001,
      "humidity": 58,
      "temp_kf": 0
    },
    "wind": {
      "speed": 2.88,
      "deg": 84,
      "gust": 3.42
    },
    "rain": {
      "3h": 0.11
    },
    "clouds": {
      "all": 100
    }
  },
  {
    "dt": 1778641200,
    "weather": [
      {
        "id": 804,
        "main": "Clouds",
        "description": "overcast clouds",
        "icon": "04d"
      }
    ],
    "main": {
      "temp": 295.71,
      "feels_like": 295.25,
      "temp_min": 295.71,
      "temp_max": 295.71,
      "pressure": 1010,
      "sea_level": 1010,
      "grnd_level": 1001,
      "humidity": 47,
      "temp_kf": 0
    },
    "wind": {
      "speed": 2.58,
      "deg": 103,
      "gust": 2.76
    },
    "clouds": {
      "all": 100
    }
  },
  {
    "dt": 1778652000,
    "weather": [
      {
        "id": 804,
        "main": "Clouds",
        "description": "overcast clouds",
        "icon": "04d"
      }
    ],
    "main": {
      "temp": 297.67,
      "feels_like": 297.3,
      "temp_min": 297.67,
      "temp_max": 297.67,
      "pressure": 1010,
      "sea_level": 1010,
      "grnd_level": 1001,
      "humidity": 43,
      "temp_kf": 0
    },
    "wind": {
      "speed": 3.16,
      "deg": 71,
      "gust": 2.91
    },
    "clouds": {
      "all": 100
    }
  },
  {
    "dt": 1778662800,
    "weather": [
      {
        "id": 804,
        "main": "Clouds",
        "description": "overcast clouds",
        "icon": "04d"
      }
    ],
    "main": {
      "temp": 296.39,
      "feels_like": 296.08,
      "temp_min": 296.39,
      "temp_max": 296.39,
      "pressure": 1010,
      "sea_level": 1010,
      "grnd_level": 1000,
      "humidity": 50,
      "temp_kf": 0
    },
    "wind": {
      "speed": 2.98,
      "deg": 89,
      "gust": 3.02
    },
    "clouds": {
      "all": 100
    }
  },
  {
    "dt": 1778673600,
    "weather": [
      {
        "id": 803,
        "main": "Clouds",
        "description": "broken clouds",
        "icon": "04n"
      }
    ],
    "main": {
      "temp": 292.03,
      "feels_like": 291.64,
      "temp_min": 292.03,
      "temp_max": 292.03,
      "pressure": 1011,
      "sea_level": 1011,
      "grnd_level": 1002,
      "humidity": 64,
      "temp_kf": 0
    },
    "wind": {
      "speed": 1.58,
      "deg": 144,
      "gust": 1.59
    },
    "clouds": {
      "all": 53
    }
  },
  {
    "dt": 1778684400,
    "weather": [
      {
        "id": 802,
        "main": "Clouds",
        "description": "scattered clouds",
        "icon": "03n"
      }
    ],
    "main": {
      "temp": 286.88,
      "feels_like": 286.27,
      "temp_min": 286.88,
      "temp_max": 286.88,
      "pressure": 1013,
      "sea_level": 1013,
      "grnd_level": 1003,
      "humidity": 75,
      "temp_kf": 0
    },
    "wind": {
      "speed": 4.36,
      "deg": 199,
      "gust": 9.52
    },
    "clouds": {
      "all": 27
    }
  },
  {
    "dt": 1778695200,
    "weather": [
      {
        "id": 803,
        "main": "Clouds",
        "description": "broken clouds",
        "icon": "04n"
      }
    ],
    "main": {
      "temp": 284.77,
      "feels_like": 283.97,
      "temp_min": 284.77,
      "temp_max": 284.77,
      "pressure": 1013,
      "sea_level": 1013,
      "grnd_level": 1004,
      "humidity": 76,
      "temp_kf": 0
    },
    "wind": {
      "speed": 5.95,
      "deg": 197,
      "gust": 14.07
    },
    "clouds": {
      "all": 64
    }
  },
  {
    "dt": 1778706000,
    "weather": [
      {
        "id": 802,
        "main": "Clouds",
        "description": "scattered clouds",
        "icon": "03d"
      }
    ],
    "main": {
      "temp": 284.92,
      "feels_like": 284.08,
      "temp_min": 284.92,
      "temp_max": 284.92,
      "pressure": 1014,
      "sea_level": 1014,
      "grnd_level": 1004,
      "humidity": 74,
      "temp_kf": 0
    },
    "wind": {
      "speed": 7.06,
      "deg": 193,
      "gust": 15.52
    },
    "clouds": {
      "all": 38
    }
  },
  {
    "dt": 1778716800,
    "weather": [
      {
        "id": 802,
        "main": "Clouds",
        "description": "scattered clouds",
        "icon": "03d"
      }
    ],
    "main": {
      "temp": 289.36,
      "feels_like": 288.5,
      "temp_min": 289.36,
      "temp_max": 289.36,
      "pressure": 1013,
      "sea_level": 1013,
      "grnd_level": 1004,
      "humidity": 56,
      "temp_kf": 0
    },
    "wind": {
      "speed": 9.25,
      "deg": 197,
      "gust": 13.09
    },
    "clouds": {
      "all": 25
    }
  },
  {
    "dt": 1778727600,
    "weather": [
      {
        "id": 803,
        "main": "Clouds",
        "description": "broken clouds",
        "icon": "04d"
      }
    ],
    "main": {
      "temp": 293.87,
      "feels_like": 293.15,
      "temp_min": 293.87,
      "temp_max": 293.87,
      "pressure": 1012,
      "sea_level": 1012,
      "grnd_level": 1003,
      "humidity": 44,
      "temp_kf": 0
    },
    "wind": {
      "speed": 9.14,
      "deg": 205,
      "gust": 11.71
    },
    "clouds": {
      "all": 71
    }
  },
  {
    "dt": 1778738400,
    "weather": [
      {
        "id": 803,
        "main": "Clouds",
        "description": "broken clouds",
        "icon": "04d"
      }
    ],
    "main": {
      "temp": 296.3,
      "feels_like": 295.66,
      "temp_min": 296.3,
      "temp_max": 296.3,
      "pressure": 1010,
      "sea_level": 1010,
      "grnd_level": 1000,
      "humidity": 38,
      "temp_kf": 0
    },
    "wind": {
      "speed": 9.12,
      "deg": 204,
      "gust": 11.92
    },
    "clouds": {
      "all": 79
    }
  },
  {
    "dt": 1778749200,
    "weather": [
      {
        "id": 804,
        "main": "Clouds",
        "description": "overcast clouds",
        "icon": "04d"
      }
    ],
    "main": {
      "temp": 293.27,
      "feels_like": 292.62,
      "temp_min": 293.27,
      "temp_max": 293.27,
      "pressure": 1008,
      "sea_level": 1008,
      "grnd_level": 999,
      "humidity": 49,
      "temp_kf": 0
    },
    "wind": {
      "speed": 8.5,
      "deg": 198,
      "gust": 14.22
    },
    "clouds": {
      "all": 92
    }
  },
  {
    "dt": 1778760000,
    "weather": [
      {
        "id": 804,
        "main": "Clouds",
        "description": "overcast clouds",
        "icon": "04n"
      }
    ],
    "main": {
      "temp": 288.44,
      "feels_like": 287.57,
      "temp_min": 288.44,
      "temp_max": 288.44,
      "pressure": 1009,
      "sea_level": 1009,
      "grnd_level": 1000,
      "humidity": 59,
      "temp_kf": 0
    },
    "wind": {
      "speed": 9.09,
      "deg": 207,
      "gust": 19.14
    },
    "clouds": {
      "all": 96
    }
  },
  {
    "dt": 1778770800,
    "weather": [
      {
        "id": 804,
        "main": "Clouds",
        "description": "overcast clouds",
        "icon": "04n"
      }
    ],
    "main": {
      "temp": 285.43,
      "feels_like": 284.59,
      "temp_min": 285.43,
      "temp_max": 285.43,
      "pressure": 1009,
      "sea_level": 1009,
      "grnd_level": 999,
      "humidity": 72,
      "temp_kf": 0
    },
    "wind": {
      "speed": 8.72,
      "deg": 207,
      "gust": 16.16
    },
    "clouds": {
      "all": 97
    }
  },
  {
    "dt": 1778781600,
    "weather": [
      {
        "id": 804,
        "main": "Clouds",
        "description": "overcast clouds",
        "icon": "04n"
      }
    ],
    "main": {
      "temp": 285.6,
      "feels_like": 284.28,
      "temp_min": 285.6,
      "temp_max": 285.6,
      "pressure": 1013,
      "sea_level": 1013,
      "grnd_level": 1003,
      "humidity": 53,
      "temp_kf": 0
    },
    "wind": {
      "speed": 5.9,
      "deg": 328,
      "gust": 11.55
    },
    "clouds": {
      "all": 99
    }
  },
  {
    "dt": 1778792400,
    "weather": [
      {
        "id": 804,
        "main": "Clouds",
        "description": "overcast clouds",
        "icon": "04d"
      }
    ],
    "main": {
      "temp": 286.41,
      "feels_like": 285.02,
      "temp_min": 286.41,
      "temp_max": 286.41,
      "pressure": 1015,
      "sea_level": 1015,
      "grnd_level": 1006,
      "humidity": 47,
      "temp_kf": 0
    },
    "wind": {
      "speed": 6.01,
      "deg": 337,
      "gust": 10.22
    },
    "clouds": {
      "all": 100
    }
  },
  {
    "dt": 1778803200,
    "weather": [
      {
        "id": 804,
        "main": "Clouds",
        "description": "overcast clouds",
        "icon": "04d"
      }
    ],
    "main": {
      "temp": 286.87,
      "feels_like": 285.16,
      "temp_min": 286.87,
      "temp_max": 286.87,
      "pressure": 1018,
      "sea_level": 1018,
      "grnd_level": 1008,
      "humidity": 33,
      "temp_kf": 0
    },
    "wind": {
      "speed": 7.09,
      "deg": 330,
      "gust": 8.04
    },
    "clouds": {
      "all": 100
    }
  }
]