[
  {
    "dt": 1779850800,
    "weather": [
      {
        "id": 804,
        "main": "Clouds",
        "description": "overcast clouds",
        "icon": "04d"
      }
    ],
    "main": {
      "temp": 293.32,
      "feels_like": 292.36,
      "temp_min": 293.32,
      "temp_max": 293.32,
      "pressure": 1012,
      "sea_level": 1012,
      "grnd_level": 1003,
      "humidity": 37,
      "temp_kf": 0
    },
    "wind": {
      "speed": 2.78,
      "deg": 12,
      "gust": 3.27
    },
    "clouds": {
      "all": 100
    }
  },
  {
    "dt": 1779861600,
    "weather": [
      {
        "id": 804,
        "main": "Clouds",
        "description": "overcast clouds",
        "icon": "04d"
      }
    ],
    "main": {
      "temp": 293.55,
      "feels_like": 292.59,
      "temp_min": 293.55,
      "temp_max": 294.02,
      "pressure": 1011,
      "sea_level": 1011,
      "grnd_level": 1001,
      "humidity": 36,
      "temp_kf": -0.47
    },
    "wind": {
      "speed": 2.42,
      "deg": 46,
      "gust": 3.3
    },
    "clouds": {
      "all": 100
    }
  },
  {
    "dt": 1779872400,
    "weather": [
      {
        "id": 804,
        "main": "Clouds",
        "description": "overcast clouds",
        "icon": "04d"
      }
    ],
    "main": {
      "temp": 293.45,
      "feels_like": 292.71,
      "temp_min": 293.45,
      "temp_max": 293.51,
      "pressure": 1010,
      "sea_level": 1010,
      "grnd_level": 1000,
      "humidity": 45,
      "temp_kf": -0.06
    },
    "wind": {
      "speed": 2.21,
      "deg": 115,
      "gust": 2.93
    },
    "clouds": {
      "all": 93
    }
  },
  {
    "dt": 1779883200,
    "weather": [
      {
        "id": 803,
        "main": "Clouds",
        "description": "broken clouds",
        "icon": "04n"
      }
    ],
    "main": {
      "temp": 287.95,
      "feels_like": 287.08,
      "temp_min": 287.95,
      "temp_max": 287.95,
      "pressure": 1009,
      "sea_level": 1009,
      "grnd_level": 999,
      "humidity": 61,
      "temp_kf": 0
    },
    "wind": {
      "speed": 1.39,
      "deg": 70,
      "gust": 1.4
    },
    "clouds": {
      "all": 62
    }
  },
  {
    "dt": 1779894000,
    "weather": [
      {
        "id": 804,
        "main": "Clouds",
        "description": "overcast clouds",
        "icon": "04n"
      }
    ],
    "main": {
      "temp": 288.11,
      "feels_like": 287.18,
      "temp_min": 288.11,
      "temp_max": 288.11,
      "pressure": 1007,
      "sea_level": 1007,
      "grnd_level": 998,
      "humidity": 58,
      "temp_kf": 0
    },
    "wind": {
      "speed": 3.27,
      "deg": 14,
      "gust": 6.07
    },
    "clouds": {
      "all": 99
    }
  },
  {
    "dt": 1779904800,
    "weather": [
      {
        "id": 500,
        "main": "Rain",
        "description": "light rain",
        "icon": "10n"
      }
    ],
    "main": {
      "temp": 286.36,
      "feels_like": 285.36,
      "temp_min": 286.36,
      "temp_max": 286.36,
      "pressure": 1006,
      "sea_level": 1006,
      "grnd_level": 996,
      "humidity": 62,
      "temp_kf": 0
    },
    "wind": {
      "speed": 5.27,
      "deg": 16,
      "gust": 10.8
    },
    "rain": {
      "3h": 0.32
    },
    "clouds": {
      "all": 99
    }
  },
  {
    "dt": 1779915600,
    "weather": [
      {
        "id": 500,
        "main": "Rain",
        "description": "light rain",
        "icon": "10d"
      }
    ],
    "main": {
      "temp": 285.78,
      "feels_like": 284.9,
      "temp_min": 285.78,
      "temp_max": 285.78,
      "pressure": 1004,
      "sea_level": 1004,
      "grnd_level": 995,
      "humidity": 69,
      "temp_kf": 0
    },
    "wind": {
      "speed": 4.91,
      "deg": 27,
      "gust": 11.92
    },
    "rain": {
      "3h": 0.13
    },
    "clouds": {
      "all": 100
    }
  },
  {
    "dt": 1779926400,
    "weather": [
      {
        "id": 500,
        "main": "Rain",
        "description": "light rain",
        "icon": "10d"
      }
    ],
    "main": {
      "temp": 285.01,
      "feels_like": 284.24,
      "temp_min": 285.01,
      "temp_max": 285.01,
      "pressure": 1002,
      "sea_level": 1002,
      "grnd_level": 993,
      "humidity": 76,
      "temp_kf": 0
    },
    "wind": {
      "speed": 6.27,
      "deg": 13,
      "gust": 11.67
    },
    "rain": {
      "3h": 0.51
    },
    "clouds": {
      "all": 100
    }
  },
  {
    "dt": 1779937200,
    "weather": [
      {
        "id": 501,
        "main": "Rain",
        "description": "moderate rain",
        "icon": "10d"
      }
    ],
    "main": {
      "temp": 283.39,
      "feels_like": 282.85,
      "temp_min": 283.39,
      "temp_max": 283.39,
      "pressure": 1000,
      "sea_level": 1000,
      "grnd_level": 990,
      "humidity": 91,
      "temp_kf": 0
    },
    "wind": {
      "speed": 7.8,
      "deg": 27,
      "gust": 12.96
    },
    "rain": {
      "3h": 5.93
    },
    "clouds": {
      "all": 100
    }
  },
  {
    "dt": 1779948000,
    "weather": [
      {
        "id": 502,
        "main": "Rain",
        "description": "heavy intensity rain",
        "icon": "10d"
      }
    ],
    "main": {
      "temp": 283.47,
      "feels_like": 283.06,
      "temp_min": 283.47,
      "temp_max": 283.47,
      "pressure": 998,
      "sea_level": 998,
      "grnd_level": 988,
      "humidity": 96,
      "temp_kf": 0
    },
    "wind": {
      "speed": 8.69,
      "deg": 10,
      "gust": 14.36
    },
    "rain": {
      "3h": 13.56
    },
    "clouds": {
      "all": 100
    }
  },
  {
    "dt": 1779958800,
    "weather": [
      {
        "id": 501,
        "main": "Rain",
        "description": "moderate rain",
        "icon": "10d"
      }
    ],
    "main": {
      "temp": 283.52,
      "feels_like": 283.09,
      "temp_min": 283.52,
      "temp_max": 283.52,
      "pressure": 998,
      "sea_level": 998,
      "grnd_level": 988,
      "humidity": 95,
      "temp_kf": 0
    },
    "wind": {
      "speed": 9.04,
      "deg": 348,
      "gust": 15.06
    },
    "rain": {
      "3h": 11.69
    },
    "clouds": {
      "all": 100
    }
  },
  {
    "dt": 1779969600,
    "weather": [
      {
        "id": 501,
        "main": "Rain",
        "description": "moderate rain",
        "icon": "10n"
      }
    ],
    "main": {
      "temp": 283.38,
      "feels_like": 282.89,
      "temp_min": 283.38,
      "temp_max": 283.38,
      "pressure": 999,
      "sea_level": 999,
      "grnd_level": 989,
      "humidity": 93,
      "temp_kf": 0
    },
    "wind": {
      "speed": 8.71,
      "deg": 344,
      "gust": 16.36
    },
    "rain": {
      "3h": 6.15
    },
    "clouds": {
      "all": 100
    }
  },
  {
    "dt": 1779980400,
    "weather": [
      {
        "id": 500,
        "main": "Rain",
        "description": "light rain",
        "icon": "10n"
      }
    ],
    "main": {
      "temp": 283.58,
      "feels_like": 282.98,
      "temp_min": 283.58,
      "temp_max": 283.58,
      "pressure": 998,
      "sea_level": 998,
      "grnd_level": 989,
      "humidity": 88,
      "temp_kf": 0
    },
    "wind": {
      "speed": 5.53,
      "deg": 321,
      "gust": 13.43
    },
    "rain": {
      "3h": 2.29
    },
    "clouds": {
      "all": 100
    }
  },
  {
    "dt": 1779991200,
    "weather": [
      {
        "id": 804,
        "main": "Clouds",
        "description": "overcast clouds",
        "icon": "04n"
      }
    ],
    "main": {
      "temp": 283.15,
      "feels_like": 280.9,
      "temp_min": 283.15,
      "temp_max": 283.15,
      "pressure": 997,
      "sea_level": 997,
      "grnd_level": 988,
      "humidity": 81,
      "temp_kf": 0
    },
    "wind": {
      "speed": 4.58,
      "deg": 327,
      "gust": 13.62
    },
    "clouds": {
      "all": 100
    }
  },
  {
    "dt": 1780002000,
    "weather": [
      {
        "id": 803,
        "main": "Clouds",
        "description": "broken clouds",
        "icon": "04d"
      }
    ],
    "main": {
      "temp": 283.12,
      "feels_like": 280.43,
      "temp_min": 283.12,
      "temp_max": 283.12,
      "pressure": 998,
      "sea_level": 998,
      "grnd_level": 989,
      "humidity": 76,
      "temp_kf": 0
    },
    "wind": {
      "speed": 5.77,
      "deg": 334,
      "gust": 13.16
    },
    "clouds": {
      "all": 79
    }
  },
  {
    "dt": 1780012800,
    "weather": [
      {
        "id": 804,
        "main": "Clouds",
        "description": "overcast clouds",
        "icon": "04d"
      }
    ],
    "main": {
      "temp": 287.34,
      "feels_like": 286.59,
      "temp_min": 287.34,
      "temp_max": 287.34,
      "pressure": 998,
      "sea_level": 998,
      "grnd_level": 988,
      "humidity": 68,
      "temp_kf": 0
    },
    "wind": {
      "speed": 6.91,
      "deg": 327,
      "gust": 10.06
    },
    "clouds": {
      "all": 89
    }
  },
  {
    "dt": 1780023600,
    "weather": [
      {
        "id": 500,
        "main": "Rain",
        "description": "light rain",
        "icon": "10d"
      }
    ],
    "main": {
      "temp": 290.93,
      "feels_like": 290.3,
      "temp_min": 290.93,
      "temp_max": 290.93,
      "pressure": 997,
      "sea_level": 997,
      "grnd_level": 988,
      "humidity": 59,
      "temp_kf": 0
    },
    "wind": {
      "speed": 8.16,
      "deg": 327,
      "gust": 11.75
    },
    "rain": {
      "3h": 0.2
    },
    "clouds": {
      "all": 100
    }
  },
  {
    "dt": 1780034400,
    "weather": [
      {
        "id": 500,
        "main": "Rain",
        "description": "light rain",
        "icon": "10d"
      }
    ],
    "main": {
      "temp": 291.36,
      "feels_like": 290.78,
      "temp_min": 291.36,
      "temp_max": 291.36,
      "pressure": 997,
      "sea_level": 997,
      "grnd_level": 988,
      "humidity": 59,
      "temp_kf": 0
    },
    "wind": {
      "speed": 5.66,
      "deg": 359,
      "gust": 13.66
    },
    "rain": {
      "3h": 0.43
    },
    "clouds": {
      "all": 100
    }
  },
  {
    "dt": 1780045200,
    "weather": [
      {
        "id": 500,
        "main": "Rain",
        "description": "light rain",
        "icon": "10d"
      }
    ],
    "main": {
      "temp": 289.35,
      "feels_like": 288.93,
      "temp_min": 289.35,
      "temp_max": 289.35,
      "pressure": 997,
      "sea_level": 997,
      "grnd_level": 987,
      "humidity": 73,
      "temp_kf": 0
    },
    "wind": {
      "speed": 4.35,
      "deg": 21,
      "gust": 8.59
    },
    "rain": {
      "3h": 0.33
    },
    "clouds": {
      "all": 100
    }
  },
  {
    "dt": 1780056000,
    "weather": [
      {
        "id": 804,
        "main": "Clouds",
        "description": "overcast clouds",
        "icon": "04n"
      }
    ],
    "main": {
      "temp": 283.48,
      "feels_like": 283.05,
      "temp_min": 283.48,
      "temp_max": 283.48,
      "pressure": 998,
      "sea_level": 998,
      "grnd_level": 989,
      "humidity": 95,
      "temp_kf": 0
    },
    "wind": {
      "speed": 2,
      "deg": 133,
      "gust": 1.36
    },
    "clouds": {
      "all": 100
    }
  },
  {
    "dt": 1780066800,
    "weather": [
      {
        "id": 803,
        "main": "Clouds",
        "description": "broken clouds",
        "icon": "04n"
      }
    ],
    "main": {
      "temp": 282.09,
      "feels_like": 280.64,
      "temp_min": 282.09,
      "temp_max": 282.09,
      "pressure": 998,
      "sea_level": 998,
      "grnd_level": 988,
      "humidity": 93,
      "temp_kf": 0
    },
    "wind": {
      "speed": 2.61,
      "deg": 191,
      "gust": 2.76
    },
    "clouds": {
      "all": 64
    }
  },
  {
    "dt": 1780077600,
    "weather": [
      {
        "id": 803,
        "main": "Clouds",
        "description": "broken clouds",
        "icon": "04n"
      }
    ],
    "main": {
      "temp": 281.94,
      "feels_like": 281.17,
      "temp_min": 281.94,
      "temp_max": 281.94,
      "pressure": 997,
      "sea_level": 997,
      "grnd_level": 988,
      "humidity": 65,
      "temp_kf": 0
    },
    "wind": {
      "speed": 1.74,
      "deg": 269,
      "gust": 1.76
    },
    "clouds": {
      "all": 51
    }
  },
  {
    "dt": 1780088400,
    "weather": [
      {
        "id": 802,
        "main": "Clouds",
        "description": "scattered clouds",
        "icon": "03d"
      }
    ],
    "main": {
      "temp": 284.24,
      "feels_like": 283.1,
      "temp_min": 284.24,
      "temp_max": 284.24,
      "pressure": 997,
      "sea_level": 997,
      "grnd_level": 987,
      "humidity": 65,
      "temp_kf": 0
    },
    "wind": {
      "speed": 2.75,
      "deg": 250,
      "gust": 5.32
    },
    "clouds": {
      "all": 39
    }
  },
  {
    "dt": 1780099200,
    "weather": [
      {
        "id": 803,
        "main": "Clouds",
        "description": "broken clouds",
        "icon": "04d"
      }
    ],
    "main": {
      "temp": 290.04,
      "feels_like": 289.38,
      "temp_min": 290.04,
      "temp_max": 290.04,
      "pressure": 995,
      "sea_level": 995,
      "grnd_level": 986,
      "humidity": 61,
      "temp_kf": 0
    },
    "wind": {
      "speed": 6.17,
      "deg": 311,
      "gust": 10.92
    },
    "clouds": {
      "all": 69
    }
  },
  {
    "dt": 1780110000,
    "weather": [
      {
        "id": 500,
        "main": "Rain",
        "description": "light rain",
        "icon": "10d"
      }
    ],
    "main": {
      "temp": 291.9,
      "feels_like": 290.95,
      "temp_min": 291.9,
      "temp_max": 291.9,
      "pressure": 996,
      "sea_level": 996,
      "grnd_level": 987,
      "humidity": 43,
      "temp_kf": 0
    },
    "wind": {
      "speed": 8.9,
      "deg": 312,
      "gust": 11.2
    },
    "rain": {
      "3h": 0.42
    },
    "clouds": {
      "all": 40
    }
  },
  {
    "dt": 1780120800,
    "weather": [
      {
        "id": 803,
        "main": "Clouds",
        "description": "broken clouds",
        "icon": "04d"
      }
    ],
    "main": {
      "temp": 290.66,
      "feels_like": 290.01,
      "temp_min": 290.66,
      "temp_max": 290.66,
      "pressure": 997,
      "sea_level": 997,
      "grnd_level": 988,
      "humidity": 59,
      "temp_kf": 0
    },
    "wind": {
      "speed": 5.48,
      "deg": 326,
      "gust": 9.14
    },
    "clouds": {
      "all": 68
    }
  },
  {
    "dt": 1780131600,
    "weather": [
      {
        "id": 804,
        "main": "Clouds",
        "description": "overcast clouds",
        "icon": "04d"
      }
    ],
    "main": {
      "temp": 290.43,
      "feels_like": 289.86,
      "temp_min": 290.43,
      "temp_max": 290.43,
      "pressure": 998,
      "sea_level": 998,
      "grnd_level": 989,
      "humidity": 63,
      "temp_kf": 0
    },
    "wind": {
      "speed": 1.87,
      "deg": 307,
      "gust": 3.91
    },
    "clouds": {
      "all": 100
    }
  },
  {
    "dt": 1780142400,
    "weather": [
      {
        "id": 804,
        "main": "Clouds",
        "description": "overcast clouds",
        "icon": "04n"
      }
    ],
    "main": {
      "temp": 285.86,
      "feels_like": 285.01,
      "temp_min": 285.86,
      "temp_max": 285.86,
      "pressure": 999,
      "sea_level": 999,
      "grnd_level": 990,
      "humidity": 70,
      "temp_kf": 0
    },
    "wind": {
      "speed": 3.27,
      "deg": 195,
      "gust": 3.38
    },
    "clouds": {
      "all": 93
    }
  },
  {
    "dt": 1780153200,
    "weather": [
      {
        "id": 800,
        "main": "Clear",
        "description": "clear sky",
        "icon": "01n"
      }
    ],
    "main": {
      "temp": 283.73,
      "feels_like": 283.04,
      "temp_min": 283.73,
      "temp_max": 283.73,
      "pressure": 1001,
      "sea_level": 1001,
      "grnd_level": 991,
      "humidity": 84,
      "temp_kf": 0
    },
    "wind": {
      "speed": 3.4,
      "deg": 206,
      "gust": 9.44
    },
    "clouds": {
      "all": 2
    }
  },
  {
    "dt": 1780164000,
    "weather": [
      {
        "id": 802,
        "main": "Clouds",
        "description": "scattered clouds",
        "icon": "03n"
      }
    ],
    "main": {
      "temp": 283.31,
      "feels_like": 282.47,
      "temp_min": 283.31,
      "temp_max": 283.31,
      "pressure": 1001,
      "sea_level": 1001,
      "grnd_level": 992,
      "humidity": 80,
      "temp_kf": 0
    },
    "wind": {
      "speed": 3.66,
      "deg": 189,
      "gust": 9.35
    },
    "clouds": {
      "all": 39
    }
  },
  {
    "dt": 1780174800,
    "weather": [
      {
        "id": 800,
        "main": "Clear",
        "description": "clear sky",
        "icon": "01d"
      }
    ],
    "main": {
      "temp": 284.84,
      "feels_like": 284.13,
      "temp_min": 284.84,
      "temp_max": 284.84,
      "pressure": 1002,
      "sea_level": 1002,
      "grnd_level": 993,
      "humidity": 79,
      "temp_kf": 0
    },
    "wind": {
      "speed": 3.38,
      "deg": 185,
      "gust": 7.42
    },
    "clouds": {
      "all": 7
    }
  },
  {
    "dt": 1780185600,
    "weather": [
      {
        "id": 801,
        "main": "Clouds",
        "description": "few clouds",
        "icon": "02d"
      }
    ],
    "main": {
      "temp": 292.44,
      "feels_like": 292.1,
      "temp_min": 292.44,
      "temp_max": 292.44,
      "pressure": 1002,
      "sea_level": 1002,
      "grnd_level": 993,
      "humidity": 64,
      "temp_kf": 0
    },
    "wind": {
      "speed": 4.67,
      "deg": 184,
      "gust": 6.37
    },
    "clouds": {
      "all": 14
    }
  },
  {
    "dt": 1780196400,
    "weather": [
      {
        "id": 803,
        "main": "Clouds",
        "description": "broken clouds",
        "icon": "04d"
      }
    ],
    "main": {
      "temp": 297.63,
      "feels_like": 297.52,
      "temp_min": 297.63,
      "temp_max": 297.63,
      "pressure": 1002,
      "sea_level": 1002,
      "grnd_level": 992,
      "humidity": 53,
      "temp_kf": 0
    },
    "wind": {
      "speed": 6.55,
      "deg": 181,
      "gust": 8.86
    },
    "clouds": {
      "all": 65
    }
  },
  {
    "dt": 1780207200,
    "weather": [
      {
        "id": 803,
        "main": "Clouds",
        "description": "broken clouds",
        "icon": "04d"
      }
    ],
    "main": {
      "temp": 298.98,
      "feels_like": 299.13,
      "temp_min": 298.98,
      "temp_max": 298.98,
      "pressure": 1000,
      "sea_level": 1000,
      "grnd_level": 991,
      "humidity": 58,
      "temp_kf": 0
    },
    "wind": {
      "speed": 6.23,
      "deg": 195,
      "gust": 13.02
    },
    "clouds": {
      "all": 76
    }
  },
  {
    "dt": 1780218000,
    "weather": [
      {
        "id": 804,
        "main": "Clouds",
        "description": "overcast clouds",
        "icon": "04d"
      }
    ],
    "main": {
      "temp": 296.45,
      "feels_like": 296.19,
      "temp_min": 296.45,
      "temp_max": 296.45,
      "pressure": 999,
      "sea_level": 999,
      "grnd_level": 990,
      "humidity": 52,
      "temp_kf": 0
    },
    "wind": {
      "speed": 9.4,
      "deg": 196,
      "gust": 20.9
    },
    "clouds": {
      "all": 98
    }
  },
  {
    "dt": 1780228800,
    "weather": [
      {
        "id": 804,
        "main": "Clouds",
        "description": "overcast clouds",
        "icon": "04n"
      }
    ],
    "main": {
      "temp": 294.02,
      "feels_like": 293.44,
      "temp_min": 294.02,
      "temp_max": 294.02,
      "pressure": 1001,
      "sea_level": 1001,
      "grnd_level": 992,
      "humidity": 49,
      "temp_kf": 0
    },
    "wind": {
      "speed": 11.25,
      "deg": 201,
      "gust": 24.24
    },
    "clouds": {
      "all": 100
    }
  },
  {
    "dt": 1780239600,
    "weather": [
      {
        "id": 803,
        "main": "Clouds",
        "description": "broken clouds",
        "icon": "04n"
      }
    ],
    "main": {
      "temp": 292.83,
      "feels_like": 292,
      "temp_min": 292.83,
      "temp_max": 292.83,
      "pressure": 1002,
      "sea_level": 1002,
      "grnd_level": 992,
      "humidity": 44,
      "temp_kf": 0
    },
    "wind": {
      "speed": 9.62,
      "deg": 200,
      "gust": 20.74
    },
    "clouds": {
      "all": 71
    }
  },
  {
    "dt": 1780250400,
    "weather": [
      {
        "id": 803,
        "main": "Clouds",
        "description": "broken clouds",
        "icon": "04n"
      }
    ],
    "main": {
      "temp": 289.67,
      "feels_like": 288.87,
      "temp_min": 289.67,
      "temp_max": 289.67,
      "pressure": 1002,
      "sea_level": 1002,
      "grnd_level": 993,
      "humidity": 57,
      "temp_kf": 0
    },
    "wind": {
      "speed": 7.65,
      "deg": 197,
      "gust": 16.33
    },
    "clouds": {
      "all": 81
    }
  },
  {
    "dt": 1780261200,
    "weather": [
      {
        "id": 802,
        "main": "Clouds",
        "description": "scattered clouds",
        "icon": "03d"
      }
    ],
    "main": {
      "temp": 289.25,
      "feels_like": 288.82,
      "temp_min": 289.25,
      "temp_max": 289.25,
      "pressure": 1004,
      "sea_level": 1004,
      "grnd_level": 995,
      "humidity": 73,
      "temp_kf": 0
    },
    "wind": {
      "speed": 5.53,
      "deg": 194,
      "gust": 12.64
    },
    "clouds": {
      "all": 41
    }
  },
  {
    "dt": 1780272000,
    "weather": [
      {
        "id": 803,
        "main": "Clouds",
        "description": "broken clouds",
        "icon": "04d"
      }
    ],
    "main": {
      "temp": 293.82,
      "feels_like": 293.59,
      "temp_min": 293.82,
      "temp_max": 293.82,
      "pressure": 1005,
      "sea_level": 1005,
      "grnd_level": 996,
      "humidity": 63,
      "temp_kf": 0
    },
    "wind": {
      "speed": 6.15,
      "deg": 200,
      "gust": 7.82
    },
    "clouds": {
      "all": 71
    }
  }
]